<?xml version="1.0" encoding="UTF-8"?><?xml-stylesheet type='text/xsl' href='_UpgradeReport_Files/UpgradeReport.xslt'?><UpgradeLog>
<Properties><Property Name="Solution" Value="TurboKeys">
</Property><Property Name="Solution File" Value="C:\Users\Virus\Documents\TurboKeys\TurboKeys\TurboKeys.sln">
</Property><Property Name="Date" Value="Friday, September 24, 2010">
</Property><Property Name="Time" Value="22:53:23 PM">
</Property></Properties><Event ErrorLevel="0" Project="Gma.UserActivityMonitor" Source="GlobalHook\Gma.UserActivityMonitor\Gma.UserActivityMonitor.csproj" Description="Project file successfully backed up as C:\Users\Virus\Documents\TurboKeys\TurboKeys\Backup\Gma.UserActivityMonitor.csproj">
</Event><Event ErrorLevel="0" Project="Gma.UserActivityMonitor" Source="GlobalHook\Gma.UserActivityMonitor\AssemblyInfo.cs" Description="File successfully backed up as C:\Users\Virus\Documents\TurboKeys\TurboKeys\Backup\AssemblyInfo.cs">
</Event><Event ErrorLevel="0" Project="Gma.UserActivityMonitor" Source="GlobalHook\Gma.UserActivityMonitor\GlobalEventProvider.cs" Description="File successfully backed up as C:\Users\Virus\Documents\TurboKeys\TurboKeys\Backup\GlobalEventProvider.cs">
</Event><Event ErrorLevel="0" Project="Gma.UserActivityMonitor" Source="GlobalHook\Gma.UserActivityMonitor\HookManager.Callbacks.cs" Description="File successfully backed up as C:\Users\Virus\Documents\TurboKeys\TurboKeys\Backup\HookManager.Callbacks.cs">
</Event><Event ErrorLevel="0" Project="Gma.UserActivityMonitor" Source="GlobalHook\Gma.UserActivityMonitor\HookManager.cs" Description="File successfully backed up as C:\Users\Virus\Documents\TurboKeys\TurboKeys\Backup\HookManager.cs">
</Event><Event ErrorLevel="0" Project="Gma.UserActivityMonitor" Source="GlobalHook\Gma.UserActivityMonitor\HookManager.Structures.cs" Description="File successfully backed up as C:\Users\Virus\Documents\TurboKeys\TurboKeys\Backup\HookManager.Structures.cs">
</Event><Event ErrorLevel="0" Project="Gma.UserActivityMonitor" Source="GlobalHook\Gma.UserActivityMonitor\HookManager.Windows.cs" Description="File successfully backed up as C:\Users\Virus\Documents\TurboKeys\TurboKeys\Backup\HookManager.Windows.cs">
</Event><Event ErrorLevel="0" Project="Gma.UserActivityMonitor" Source="GlobalHook\Gma.UserActivityMonitor\MouseEventExtArgs.cs" Description="File successfully backed up as C:\Users\Virus\Documents\TurboKeys\TurboKeys\Backup\MouseEventExtArgs.cs">
</Event><Event ErrorLevel="1" Project="Gma.UserActivityMonitor" Source="GlobalHook\Gma.UserActivityMonitor\Gma.UserActivityMonitor.csproj" Description="Your project is targeting .NET Framework 2.0 or 3.0. If your project uses assemblies requiring a newer .NET Framework, your project will fail to build. You can change the .NET Framework version by clicking Properties on the project menu and then selecting a new version in the '.NET Framework' dropdown box. (In Visual Basic, this is located on the Compile tab by clicking the 'Advanced Compiler Options...' button.)">
</Event><Event ErrorLevel="0" Project="Gma.UserActivityMonitor" Source="GlobalHook\Gma.UserActivityMonitor\Gma.UserActivityMonitor.csproj" Description="Project converted successfully">
</Event><Event ErrorLevel="3" Project="Gma.UserActivityMonitor" Source="GlobalHook\Gma.UserActivityMonitor\Gma.UserActivityMonitor.csproj" Description="Converted">
</Event><Event ErrorLevel="0" Project="Gma.UserActivityMonitor" Source="GlobalHook\Gma.UserActivityMonitor\Gma.UserActivityMonitor.csproj" Description="Scan complete: Upgrade not required for project files.">
</Event></UpgradeLog>